mcp_apple_notes/__init__.py
mcp_apple_notes/server.py
mcp_apple_notes/applescript/__init__.py
mcp_apple_notes/applescript/base_operations.py
mcp_apple_notes/applescript/create_folder.py
mcp_apple_notes/applescript/create_note.py
mcp_apple_notes/applescript/delete_folder.py
mcp_apple_notes/applescript/delete_note.py
mcp_apple_notes/applescript/folder_structure.py
mcp_apple_notes/applescript/list_notes.py
mcp_apple_notes/applescript/move_folder.py
mcp_apple_notes/applescript/move_note.py
mcp_apple_notes/applescript/note_id_utils.py
mcp_apple_notes/applescript/notes_structure.py
mcp_apple_notes/applescript/read_folder.py
mcp_apple_notes/applescript/read_note.py
mcp_apple_notes/applescript/rename_folder.py
mcp_apple_notes/applescript/search_notes.py
mcp_apple_notes/applescript/update_note.py
mcp_apple_notes/applescript/validation_utils.py
mcp_apple_notes/tools/__init__.py
mcp_apple_notes/tools/notes_tools.py
mcp_apple_notes-0.1.2.dist-info/METADATA
mcp_apple_notes-0.1.2.dist-info/WHEEL
mcp_apple_notes-0.1.2.dist-info/entry_points.txt
mcp_apple_notes-0.1.2.dist-info/licenses/LICENSE
mcp_apple_notes-0.1.2.dist-info/RECORD
