Metadata-Version: 2.4
Name: mcp-apple-notes
Version: 0.1.2
Summary: MCP server for Apple Notes integration using AppleScript
Project-URL: Homepage, https://github.com/henilcalagiya/mcp-apple-notes
Project-URL: Documentation, https://github.com/henilcalagiya/mcp-apple-notes#readme
Project-URL: Repository, https://github.com/henilcalagiya/mcp-apple-notes
Project-URL: Issues, https://github.com/henilcalagiya/mcp-apple-notes/issues
Project-URL: Changelog, https://github.com/henilcalagiya/mcp-apple-notes/releases
Author-email: Henil C Alagiya <henilcalagiya@gmail.com>
Maintainer-email: Henil C Alagiya <henilcalagiya@gmail.com>
License: MIT
License-File: LICENSE
Keywords: ai,apple-notes,applescript,automation,llm,mcp
Classifier: Development Status :: 4 - Beta
Classifier: Intended Audience :: Developers
Classifier: License :: OSI Approved :: MIT License
Classifier: Operating System :: MacOS
Classifier: Programming Language :: Python :: 3
Classifier: Programming Language :: Python :: 3.10
Classifier: Programming Language :: Python :: 3.11
Classifier: Programming Language :: Python :: 3.12
Classifier: Programming Language :: Python :: 3.13
Classifier: Topic :: Software Development :: Libraries :: Python Modules
Classifier: Topic :: System :: Systems Administration
Classifier: Topic :: Utilities
Requires-Python: >=3.10
Requires-Dist: aiofiles>=23.0.0
Requires-Dist: mcp[cli]>=1.12.4
Requires-Dist: pydantic>=2.0.0
Requires-Dist: rich>=13.0.0
Requires-Dist: typing-extensions>=4.0.0
Provides-Extra: dev
Requires-Dist: black>=23.0.0; extra == 'dev'
Requires-Dist: isort>=5.12.0; extra == 'dev'
Requires-Dist: mypy>=1.0.0; extra == 'dev'
Requires-Dist: pytest-asyncio>=0.21.0; extra == 'dev'
Requires-Dist: pytest>=7.0.0; extra == 'dev'
Requires-Dist: ruff>=0.1.0; extra == 'dev'
